indOCRArmy/__init__.py
indOCRArmy/drawer.py
indOCRArmy/gdrive_utils.py
indOCRArmy/modelOCR.py
indOCRArmy-0.1.13.dist-info/LICENSE
indOCRArmy-0.1.13.dist-info/METADATA
indOCRArmy-0.1.13.dist-info/WHEEL
indOCRArmy-0.1.13.dist-info/top_level.txt
indOCRArmy-0.1.13.dist-info/RECORD
