Metadata-Version: 2.1
Name: indOCRArmy
Version: 0.1.13
Summary: A package for reading id and name on KTP and SIM
Home-page: UNKNOWN
Author: Mulya Rahardja Madjiah, Andreas; Hervind; S Fawwazi, Ziyad
Author-email: ziyad.syauqi95@gmail.com
License: UNKNOWN
Platform: UNKNOWN
Classifier: Programming Language :: Python :: 3
Classifier: License :: OSI Approved :: MIT License
Classifier: Operating System :: OS Independent
Requires-Python: >=3.7
Requires-Dist: requests
Requires-Dist: numpy
Requires-Dist: opencv-contrib-python
Requires-Dist: pandas
Requires-Dist: Pillow
Requires-Dist: matplotlib
